TL_GPRSM/__init__.py
TL_GPRSM/__version__.py
TL_GPRSM/models/GPRSM.py
TL_GPRSM/models/__init__.py
TL_GPRSM/utils/__init__.py
TL_GPRSM/utils/metrics.py
TL_GPRSM/utils/sampling.py
TL_GPRSM-0.1.0.dist-info/LICENSE
TL_GPRSM-0.1.0.dist-info/METADATA
TL_GPRSM-0.1.0.dist-info/WHEEL
TL_GPRSM-0.1.0.dist-info/top_level.txt
TL_GPRSM-0.1.0.dist-info/RECORD
