Metadata-Version: 2.1
Name: TL-GPRSM
Version: 0.1.0
Summary: TL-GPRSM: Tlansfer Learning Gaussian Process Regression Surrogate Model
Home-page: https://github.com/SaidaTaisei/TL-GPRSM
Author: Taisei Saida
Author-email: saida.taisei.tj@alumni.tsukuba.ac.jp
Maintainer: Taisei Saida
Maintainer-email: saida.taisei.tj@alumni.tsukuba.ac.jp
License: MIT License
Download-URL: https://github.com/SaidaTaisei/TL-GPRSM
Platform: UNKNOWN
Classifier: Intended Audience :: Science/Research
Classifier: License :: OSI Approved :: MIT License
Classifier: Programming Language :: Python :: 3.8
Classifier: Programming Language :: Python :: 3.9
Classifier: Programming Language :: Python :: 3.10
Classifier: Topic :: Scientific/Engineering
Requires-Python: >=3.8
Requires-Dist: numpy (<=1.23.0,>=1.7)
Requires-Dist: GPy (>=1.10.0)
Requires-Dist: h5py (>=3.1.0)
